minuteman/__init__.py
minuteman/core.py
minuteman/parser.py
minuteman/units.py
minuteman-0.1.0.dist-info/LICENSE
minuteman-0.1.0.dist-info/METADATA
minuteman-0.1.0.dist-info/WHEEL
minuteman-0.1.0.dist-info/top_level.txt
minuteman-0.1.0.dist-info/RECORD
