Metadata-Version: 2.1
Name: minuteman
Version: 0.1.0
Summary: Represent and transform expressions of time eg. '5 minutes a day in a year in days' = 1.27 days.
Home-page: https://github.com/stscoundrel/python-template
Author: stscoundrel
Requires-Python: >=3.9
License-File: LICENSE
